gqlite/__init__.py
gqlite/gqlite.cpython-310-x86_64-linux-gnu.so
gqlitedb-1.5.0.dist-info/METADATA
gqlitedb-1.5.0.dist-info/WHEEL
gqlitedb-1.5.0.dist-info/RECORD
