Metadata-Version: 2.4
Name: gqlitedb
Version: 1.5.0
Classifier: Programming Language :: Rust
Classifier: Programming Language :: Python :: Implementation :: CPython
Classifier: Programming Language :: Python :: Implementation :: PyPy
Classifier: License :: OSI Approved :: MIT License
Classifier: Operating System :: OS Independent
Summary: Python bindings for GQLite, a Graph Query library
Home-Page: https://gqlite.org
Author: Cyrille Berger
Requires-Python: >=3.9
Project-URL: Bug Tracker, https://github.com/auksys/gqlite/issues
Project-URL: Homepage, https://gitlab.com/auksys/gqlite
